dependency_injection/__init__.py
dependency_injection/container.py
dependency_injection/decorator.py
dependency_injection/registration.py
dependency_injection/scope.py
dependency_injection/serialization.py
dependency_injection/tags/__init__.py
dependency_injection/tags/all_tagged.py
dependency_injection/tags/any_tagged.py
dependency_injection/tags/tagged.py
dependency_injection/utils/__init__.py
dependency_injection/utils/singleton_meta.py
py_dependency_injection-1.0.0a10.dist-info/LICENSE
py_dependency_injection-1.0.0a10.dist-info/METADATA
py_dependency_injection-1.0.0a10.dist-info/WHEEL
py_dependency_injection-1.0.0a10.dist-info/top_level.txt
py_dependency_injection-1.0.0a10.dist-info/RECORD
