Metadata-Version: 2.1
Name: py-dependency-injection
Version: 1.0.0a10
Summary: A dependency injection library for Python.
Home-page: https://github.com/runemalm/py-dependency-injection
Author: David Runemalm, 2024
Author-email: david.runemalm@gmail.com
License: GNU General Public License v3.0
Project-URL: Documentation, https://py-dependency-injection.readthedocs.io/en/latest/
Project-URL: Bug Tracker, https://github.com/runemalm/py-dependency-injection/issues
Classifier: Development Status :: 3 - Alpha
Classifier: Intended Audience :: Developers
Classifier: License :: OSI Approved :: GNU General Public License v3 (GPLv3)
Classifier: Programming Language :: Python :: 3.7
Classifier: Programming Language :: Python :: 3.8
Classifier: Programming Language :: Python :: 3.9
Classifier: Programming Language :: Python :: 3.10
Classifier: Programming Language :: Python :: 3.11
Classifier: Programming Language :: Python :: 3.12
Classifier: Topic :: Software Development :: Libraries :: Python Modules
Requires-Python: >=3.7
License-File: LICENSE
